syft_rpc/__init__.py
syft_rpc/protocol.py
syft_rpc/py.typed
syft_rpc/rpc.py
syft_rpc/rpc_db.py
syft_rpc/util.py
syft_rpc-0.4.1.dist-info/METADATA
syft_rpc-0.4.1.dist-info/WHEEL
syft_rpc-0.4.1.dist-info/RECORD
